lordoftherings/__init__.py
lordoftherings/lordoftherings.py
tests/__init__.py
tests/test_lordoftherings.py
tests/test_usage.py
AaronBlaser_SDK-1.0.1.dist-info/METADATA
AaronBlaser_SDK-1.0.1.dist-info/WHEEL
AaronBlaser_SDK-1.0.1.dist-info/top_level.txt
AaronBlaser_SDK-1.0.1.dist-info/RECORD
