Metadata-Version: 2.1
Name: AaronBlaser-SDK
Version: 1.0.1
Summary: SDK for the lord of the rings API
Home-page: https://github.com/ablaser5/AaronBlaser-SDK
Author: Aaron Blaser
Author-email: ablaser5@comcast.net
Classifier: License :: OSI Approved :: MIT License
Classifier: Programming Language :: Python :: 3
Classifier: Programming Language :: Python :: 3.7
Requires-Dist: certifi (==2023.5.7)
Requires-Dist: charset-normalizer (==3.1.0)
Requires-Dist: idna (==3.4)
Requires-Dist: requests (==2.31.0)
Requires-Dist: urllib3 (==2.0.2)
